setup.py
upsmychoice/__init__.py
upsmychoice.egg-info/PKG-INFO
upsmychoice.egg-info/SOURCES.txt
upsmychoice.egg-info/dependency_links.txt
upsmychoice.egg-info/requires.txt
upsmychoice.egg-info/top_level.txt