Metadata-Version: 1.1
Name: upsmychoice
Version: 1.0.2
Summary: Python 3 API for UPS My Choice, a way to track packages.
Home-page: https://github.com/happyleavesaoc/python-upsmychoice/
Author: happyleaves
Author-email: happyleaves.tfr@gmail.com
License: MIT
Platform: UNKNOWN
Classifier: License :: OSI Approved :: MIT License
Classifier: Operating System :: OS Independent
Classifier: Programming Language :: Python :: 3
